{
  "last-release-sha": "c7f3f9afba466a150f90e374f8a401daf1a56d11",
  "packages": {
    ".": {
      "release-type": "node",
      "extra-files": ["app/package.json"],
      "changelog-sections": [
        { "type": "feat", "section": "🎉 Features", "hidden": false },
        { "type": "fix", "section": "🛠️ Fixes", "hidden": false },
        { "type": "docs", "section": "📄 Documentation", "hidden": false },
        { "type": "perf", "section": "⚡ Performance", "hidden": false },
        { "type": "refactor", "section": "🏗️ Refactor", "hidden": false },
        { "type": "chore", "section": "♻️ Chores", "hidden": true },
        { "type": "test", "section": "♻️ Chores", "hidden": true },
        { "type": "build", "section": "⚙️ Automation", "hidden": true },
        { "type": "ci", "section": "⚙️ Automation", "hidden": true }
      ]
    }
  }
}
